Metadata-Version: 2.1
Name: discriminative_lexicon_model
Version: 1.4
Summary: Discriminative Lexicon Model in Python
Home-page: https://github.com/msaito8623/discriminative_lexicon_model
Author: Motoki Saito
Author-email: motoki.saito@uni-tuebingen.de
License: MIT
Classifier: Development Status :: 3 - Alpha
Classifier: Environment :: Console
Classifier: Intended Audience :: Science/Research
Classifier: License :: OSI Approved :: MIT License
Classifier: Operating System :: POSIX :: Linux
Classifier: Operating System :: MacOS
Classifier: Operating System :: Microsoft :: Windows
Classifier: Programming Language :: Python
Classifier: Programming Language :: Python :: 3.11
Classifier: Programming Language :: Python :: 3 :: Only
Classifier: Topic :: Scientific/Engineering
License-File: LICENSE.txt
Requires-Dist: pandas
Requires-Dist: numpy
Requires-Dist: xarray
Requires-Dist: scipy
Requires-Dist: fasttext
Requires-Dist: tqdm
Provides-Extra: tests
Requires-Dist: pytest; extra == "tests"
Provides-Extra: docs
Requires-Dist: sphinx; extra == "docs"
Requires-Dist: sphinx_rtd_theme; extra == "docs"
